idugeoserverclient/__init__.py
idugeoserverclient/_version.py
idugeoserverclient/client/__init__.py
idugeoserverclient/client/client_interface.py
idugeoserverclient/client/implementations/__init__.py
idugeoserverclient/client/implementations/client.py
idugeoserverclient/models/__init__.py
idugeoserverclient/models/datastore_model.py
idugeoserverclient/models/layer_model.py
idugeoserverclient-0.3.1.dist-info/METADATA
idugeoserverclient-0.3.1.dist-info/WHEEL
idugeoserverclient-0.3.1.dist-info/RECORD
