Metadata-Version: 2.1
Name: IduGeoserverClient
Version: 0.3.1
Summary: --/--
License: BSD-3-Clause
Author: soldey
Author-email: 71354808+soldey@users.noreply.github.com
Requires-Python: >=3.10,<3.12
Classifier: License :: OSI Approved :: BSD License
Classifier: Programming Language :: Python :: 3
Classifier: Programming Language :: Python :: 3.10
Classifier: Programming Language :: Python :: 3.11
Requires-Dist: aiohttp (>=3.11.2,<4.0.0)
Requires-Dist: idu-config (>=1.0.2,<2.0.0)
Requires-Dist: idu-redis-client (>=1.0.0,<2.0.0)
Requires-Dist: loguru (>=0.7.2,<0.8.0)
